LICENSE
MANIFEST.in
README.rst
config.cfg
setup.py
financial_statements_downloader/__init__.py
financial_statements_downloader/__main__.py
financial_statements_downloader/cli.py
financial_statements_downloader/data.py
financial_statements_downloader/downloader.py
financial_statements_downloader/parser.py
financial_statements_downloader.egg-info/PKG-INFO
financial_statements_downloader.egg-info/SOURCES.txt
financial_statements_downloader.egg-info/dependency_links.txt
financial_statements_downloader.egg-info/entry_points.txt
financial_statements_downloader.egg-info/not-zip-safe
financial_statements_downloader.egg-info/requires.txt
financial_statements_downloader.egg-info/top_level.txt
tests/test_data.py
tests/test_downloader.py
tests/test_parser.py
tests/fixtures/configs/config.cfg
tests/fixtures/database/db.json
tests/fixtures/documents/00014028/B 24_SL57_KSCB.pdf
tests/fixtures/documents/00014028/B 24_SL9_KSCB.pdf
tests/fixtures/icos/icos1.csv
tests/fixtures/icos/icos2.csv
tests/fixtures/statements/test.pdf