Metadata-Version: 1.1
Name: financial-statements-downloader
Version: 0.1.1
Summary: Simple application for downloading financial statements from czech business register.
Home-page: https://github.com/jan-stanek/financial-statements-downloader
Author: Jan Staněk
Author-email: stanej16@fit.cvut.cz
License: MIT
Keywords: czech republic financial statements business register
Platform: UNKNOWN
Classifier: Development Status :: 4 - Beta
Classifier: Environment :: Console
Classifier: Intended Audience :: Developers
Classifier: Intended Audience :: Education
Classifier: Intended Audience :: Information Technology
Classifier: Intended Audience :: Science/Research
Classifier: License :: OSI Approved :: MIT License
Classifier: Natural Language :: English
Classifier: Programming Language :: Python
Classifier: Programming Language :: Python :: 3
Classifier: Programming Language :: Python :: 3.6
Classifier: Topic :: Utilities
